piepilot/__init__.py
piepilot/version.py
PiePilot-0.0.2.dist-info/LICENSE.txt
PiePilot-0.0.2.dist-info/METADATA
PiePilot-0.0.2.dist-info/WHEEL
PiePilot-0.0.2.dist-info/entry_points.txt
PiePilot-0.0.2.dist-info/top_level.txt
PiePilot-0.0.2.dist-info/RECORD
